euler/__init__.py
euler/main.py
EulerNumber-0.1.1.dist-info/METADATA
EulerNumber-0.1.1.dist-info/WHEEL
EulerNumber-0.1.1.dist-info/top_level.txt
EulerNumber-0.1.1.dist-info/RECORD
