Metadata-Version: 2.1
Name: EulerNumber
Version: 0.1.1
Summary: This library shows the euler number
Home-page: https://github.com/kaMod4/euler
Author: Ivan Miskin
Author-email: navi.niksim@gmail.com
License: MIT
Classifier: Programming Language :: Python :: 3
Classifier: License :: OSI Approved :: MIT License
Classifier: Operating System :: OS Independent
Requires-Python: >=3.6
